{
    "name": "Food",
    "tag": "Food",
    "components": [
        {
            "type": "Transform",
            "position": {
                "x": 0,
                "y": 0,
                "z": 0
            },
            "rotation": 0,
            "scale": 1
        },
        {
            "type": "Model",
            "path": "../src/assets/models/tiles/items/bomb.obj",
            "position": {
                "x": 0,
                "y": 10,
                "z": 0
            },
            "scale": 1
        }
    ]
}
